djjunopass
